setup.py
timesuck/__init__.py
timesuck/migrate.py
timesuck/reports.py
timesuck.egg-info/PKG-INFO
timesuck.egg-info/SOURCES.txt
timesuck.egg-info/dependency_links.txt
timesuck.egg-info/entry_points.txt
timesuck.egg-info/top_level.txt