Metadata-Version: 1.0
Name: timesuck
Version: 0.1
Summary: Generate reports from your timesuck database
Home-page: http://github.com/derferman/timesuck
Author: Kyle Conroy
Author-email: kyle@twilio.com
License: UNKNOWN
Keywords: time tracking,timesuck
Platform: UNKNOWN
Classifier: Intended Audience :: Developers
Classifier: License :: OSI Approved :: MIT License
Classifier: Operating System :: OS Independent
Classifier: Programming Language :: Python
Classifier: Programming Language :: Python :: 2.7
Classifier: Topic :: Software Development :: Libraries :: Python Modules
